client/__init__.py
client/add_my_dataset.py
client/client.py
client/example_funcs.py
client/openapi.py
client/upload_jsonl.py
client/utils_datalab.py
client/utils_funcs.py
client/resources/__init__.py
client/resources/gender_data/__init__.py
datalabs/__init__.py
datalabs/arrow_dataset.py
datalabs/arrow_reader.py
datalabs/arrow_writer.py
datalabs/builder.py
datalabs/combine.py
datalabs/config.py
datalabs/constants.py
datalabs/data_files.py
datalabs/dataset_dict.py
datalabs/enums.py
datalabs/fingerprint.py
datalabs/info.py
datalabs/inspect.py
datalabs/iterable_dataset.py
datalabs/keyhash.py
datalabs/load.py
datalabs/metric.py
datalabs/naming.py
datalabs/prompt.py
datalabs/py.typed
datalabs/search.py
datalabs/splits.py
datalabs/streaming.py
datalabs/table.py
datalabs/task_dataset.py
datalabs/commands/__init__.py
datalabs/commands/convert.py
datalabs/commands/datasets_cli.py
datalabs/commands/dummy_data.py
datalabs/commands/env.py
datalabs/commands/run_beam.py
datalabs/features/__init__.py
datalabs/features/audio.py
datalabs/features/features.py
datalabs/features/translation.py
datalabs/filesystems/__init__.py
datalabs/filesystems/compression.py
datalabs/filesystems/hffilesystem.py
datalabs/filesystems/s3filesystem.py
datalabs/formatting/__init__.py
datalabs/formatting/formatting.py
datalabs/formatting/jax_formatter.py
datalabs/formatting/tf_formatter.py
datalabs/io/__init__.py
datalabs/io/abc.py
datalabs/io/csv.py
datalabs/io/json.py
datalabs/io/parquet.py
datalabs/io/text.py
datalabs/operations/__init__.py
datalabs/operations/data.py
datalabs/operations/operation.py
datalabs/operations/tokenizer.py
datalabs/operations/aggregate/__init__.py
datalabs/operations/aggregate/aggregating.py
datalabs/operations/aggregate/auto_eval.py
datalabs/operations/aggregate/general.py
datalabs/operations/aggregate/kg_link_prediction.py
datalabs/operations/aggregate/qa_extractive.py
datalabs/operations/aggregate/qa_multiple_choice.py
datalabs/operations/aggregate/sequence_labeling.py
datalabs-0.4.15.dist-info/LICENSE
datalabs-0.4.15.dist-info/METADATA
datalabs-0.4.15.dist-info/WHEEL
datalabs-0.4.15.dist-info/entry_points.txt
datalabs-0.4.15.dist-info/top_level.txt
datalabs-0.4.15.dist-info/RECORD
