Metadata-Version: 2.1
Name: datalabs
Version: 0.4.15
Summary: Datalabs
Home-page: https://github.com/expressai/datalab
Author: expressai
Author-email: stefanpengfei@gamil.com
License: Apache 2.0
Download-URL: https://github.com/expressai/datalab/tags
Keywords: dataset
Platform: UNKNOWN
Classifier: Development Status :: 5 - Production/Stable
Classifier: Intended Audience :: Developers
Classifier: Intended Audience :: Education
Classifier: Intended Audience :: Science/Research
Classifier: License :: OSI Approved :: Apache Software License
Classifier: Operating System :: OS Independent
Classifier: Programming Language :: Python :: 3
Classifier: Programming Language :: Python :: 3.6
Classifier: Programming Language :: Python :: 3.7
Classifier: Topic :: Scientific/Engineering :: Artificial Intelligence
License-File: LICENSE
Requires-Dist: numpy (>=1.17)
Requires-Dist: pyarrow (!=4.0.0,>=3.0.0)
Requires-Dist: dill
Requires-Dist: pandas
Requires-Dist: requests (>=2.19.0)
Requires-Dist: tqdm (>=4.62.1)
Requires-Dist: xxhash
Requires-Dist: multiprocess
Requires-Dist: pathos
Requires-Dist: fsspec[http] (>=2021.05.0)
Requires-Dist: aiohttp
Requires-Dist: huggingface-hub (<1.0.0,>=0.1.0)
Requires-Dist: packaging
Requires-Dist: pymongo[srv]
Requires-Dist: spacy
Requires-Dist: checklist
Requires-Dist: lexicalrichness
Requires-Dist: sacrebleu
Requires-Dist: compare-mt
Requires-Dist: scikit-learn
Requires-Dist: seqeval
Requires-Dist: jieba
Requires-Dist: apache-beam
Requires-Dist: dataclasses ; python_version < "3.7"
Requires-Dist: importlib-metadata ; python_version < "3.8"
Provides-Extra: dev
Requires-Dist: pre-commit ; extra == 'dev'
Provides-Extra: quality
Requires-Dist: pre-commit ; extra == 'quality'
Provides-Extra: tests
